{
  "rule_id": "CTR005",
  "rule_name": "Trend Continuation",
  "category": "TR",
  "subcategory": "Trend Composite",
  "version": "1.0.0",
  "status": "Frozen",
  "priority": "Medium",
  "weight": 1.0,
  "description": "Trend Continuation",
  "inputs": [],
  "outputs": [],
  "dependencies": [],
  "tags": [
    "Catalog",
    "Composite",
    "CTR"
  ],
  "mvp_operational": true,
  "lifecycle_stage": "Adopted",
  "updated_at": "2026-06-20",
  "implementation": "engine/rules/composite/ctr.py",
  "backtest_verdict": "ADOPT",
  "backtest_evaluated_at": "2026-06-30T01:20:12Z",
  "backtest_symbols": 30
}
